LICENSE
MANIFEST.in
README.md
pyproject.toml
setup.py
src/zwo_eaf.c
src/zwo_eaf.pyx
src/EAF_linux_mac_SDK_V1.6/include/EAF_focuser.h
src/EAF_linux_mac_SDK_V1.6/lib/x64/libEAFFocuser.a
src/EAF_linux_mac_SDK_V1.6/lib/x64/libEAFFocuser.so
src/EAF_linux_mac_SDK_V1.6/lib/x64/libEAFFocuser.so.1.6
src/zwo_eaf.egg-info/PKG-INFO
src/zwo_eaf.egg-info/SOURCES.txt
src/zwo_eaf.egg-info/dependency_links.txt
src/zwo_eaf.egg-info/top_level.txt