Metadata-Version: 2.1
Name: zwo_eaf
Version: 1.0.2
Summary: Python wrapper for ZWO EAF C++ SDK
Author: Eric Pedley
Project-URL: source, https://github.com/EricPedley/py-zwo-eaf
License-File: LICENSE
